{
  "dependencies": {
    "mssql1": {
      "resourceId": "/subscriptions/[parameters('subscriptionId')]/resourcegroups/[parameters('resourceGroupName')]/providers/Microsoft.Sql/servers/g08-project2021dbserver/databases/G08_Project2021_dotNet",
      "type": "mssql.azure",
      "connectionId": "DefaultConnection",
      "secretStore": "AzureAppSettings"
    },
    "secrets1": {
      "resourceId": "/subscriptions/[parameters('subscriptionId')]/resourceGroups/[parameters('resourceGroupName')]/providers/Microsoft.KeyVault/vaults/G08Project2021vault",
      "type": "secrets.keyVault",
      "connectionId": "VaultUri",
      "secretStore": "AzureAppSettings"
    }
  }
}